fileconv/__init__.py
fileconv/cli.py
fileconv/crawlers.py
fileconv/office_to_pdf.py
fileconv/pdf_to_txt.py
fileconv/txt_to_pdf.py
fileconv-0.0.3.dist-info/LICENSE
fileconv-0.0.3.dist-info/METADATA
fileconv-0.0.3.dist-info/WHEEL
fileconv-0.0.3.dist-info/entry_points.txt
fileconv-0.0.3.dist-info/top_level.txt
fileconv-0.0.3.dist-info/RECORD
