Metadata-Version: 2.1
Name: fileconv
Version: 0.0.3
Summary: This CLI converts text an MS Word and MS Excel files to PDF files
Home-page: https://github.com/ovanov/fileconv
Author: ovanov
Author-email: ovanov@protonmail.com
License: MIT
Keywords: FITS,xml,csv,CLI programm
Platform: any
Classifier: Development Status :: 3 - Alpha
Classifier: Intended Audience :: Developers
Classifier: Topic :: Software Development :: Build Tools
Classifier: License :: OSI Approved :: MIT License
Classifier: Programming Language :: Python :: 3
Classifier: Programming Language :: Python :: 3.6
Classifier: Programming Language :: Python :: 3.7
Classifier: Programming Language :: Python :: 3.8
Classifier: Programming Language :: Python :: 3.9
Requires-Python: >=3.6
License-File: LICENSE
Requires-Dist: fpdf (>=1.7.2)
Requires-Dist: pywin32 (>=227)
Requires-Dist: PyPDF2 (>=1.26.0)
Requires-Dist: tqdm (>=4.61.2)
